huaweicloudsdkdeh/__init__.py
huaweicloudsdkdeh/v1/__init__.py
huaweicloudsdkdeh/v1/deh_async_client.py
huaweicloudsdkdeh/v1/deh_client.py
huaweicloudsdkdeh/v1/model/__init__.py
huaweicloudsdkdeh/v1/model/batch_create_dedicated_host_tags_request.py
huaweicloudsdkdeh/v1/model/batch_create_dedicated_host_tags_response.py
huaweicloudsdkdeh/v1/model/batch_delete_dedicated_host_tags_request.py
huaweicloudsdkdeh/v1/model/batch_delete_dedicated_host_tags_response.py
huaweicloudsdkdeh/v1/model/create_dedicated_host_request.py
huaweicloudsdkdeh/v1/model/create_dedicated_host_response.py
huaweicloudsdkdeh/v1/model/dedicated_host_type.py
huaweicloudsdkdeh/v1/model/dedicated_host_type_offering.py
huaweicloudsdkdeh/v1/model/delete_dedicated_host_request.py
huaweicloudsdkdeh/v1/model/delete_dedicated_host_response.py
huaweicloudsdkdeh/v1/model/list_dedicated_host_all_types_request.py
huaweicloudsdkdeh/v1/model/list_dedicated_host_all_types_response.py
huaweicloudsdkdeh/v1/model/list_dedicated_host_tags_request.py
huaweicloudsdkdeh/v1/model/list_dedicated_host_tags_response.py
huaweicloudsdkdeh/v1/model/list_dedicated_host_types_request.py
huaweicloudsdkdeh/v1/model/list_dedicated_host_types_response.py
huaweicloudsdkdeh/v1/model/list_dedicated_hosts_by_tags_request.py
huaweicloudsdkdeh/v1/model/list_dedicated_hosts_by_tags_response.py
huaweicloudsdkdeh/v1/model/list_dedicated_hosts_request.py
huaweicloudsdkdeh/v1/model/list_dedicated_hosts_response.py
huaweicloudsdkdeh/v1/model/list_resource_tag.py
huaweicloudsdkdeh/v1/model/list_servers_dedicated_host_request.py
huaweicloudsdkdeh/v1/model/list_servers_dedicated_host_response.py
huaweicloudsdkdeh/v1/model/match.py
huaweicloudsdkdeh/v1/model/page_info.py
huaweicloudsdkdeh/v1/model/req_allocate_deh.py
huaweicloudsdkdeh/v1/model/req_allocate_deh_extend_param.py
huaweicloudsdkdeh/v1/model/req_list_deh_by_tags.py
huaweicloudsdkdeh/v1/model/req_set_or_delete_tags.py
huaweicloudsdkdeh/v1/model/req_update_deh.py
huaweicloudsdkdeh-3.1.184.dist-info/METADATA
huaweicloudsdkdeh-3.1.184.dist-info/WHEEL
huaweicloudsdkdeh-3.1.184.dist-info/licenses/LICENSE
huaweicloudsdkdeh-3.1.184.dist-info/RECORD
